[
  {
    "id": "f4a9e56e-6b1c-4b6e-8e3d-bdc0fce125d1",
    "name": "Participación Deportiva Juvenil",
    "category": "Deportes",
    "description": "Encuesta para analizar la frecuencia y tipos de deportes practicados por jóvenes entre 15 y 25 años.",
    "image": "https://images.pexels.com/photos/17982933/pexels-photo-17982933.jpeg?_gl=1*djcpxi*_ga*MTY3MjI4OTIzNy4xNzIyNzk0Mjcw*_ga_8JE65Q40S6*czE3NTI2MzUwNjQkbzYkZzEkdDE3NTI2MzUwODAkajQ0JGwwJGgw"
  },
  {
    "id": "a2c5b15f-90f2-4039-91d7-13fa4d870b93",
    "name": "Salud Pública y Bienestar",
    "category": "Salud Pública",
    "description": "Recopilación de datos sobre hábitos saludables y acceso a servicios médicos en la comunidad.",
    "image": "https://images.pexels.com/photos/32961444/pexels-photo-32961444.jpeg"
  },
  {
    "id": "e9a7823a-f1dc-4f1e-86bb-f20e93326f4e",
    "name": "Opinión sobre Educación a Distancia",
    "category": "Educación",
    "description": "Encuesta que busca conocer la percepción de estudiantes y profesores acerca de la educación online.",
    "image": "https://images.pexels.com/photos/6393342/pexels-photo-6393342.jpeg"
  },
  {
    "id": "bd13757b-994a-4d27-9124-6758de578d36",
    "name": "Conciencia Ambiental y Reciclaje",
    "category": "Medio Ambiente",
    "description": "Investigación sobre prácticas de reciclaje y conciencia ecológica en diferentes zonas urbanas.",
    "image": "https://images.pexels.com/photos/7656992/pexels-photo-7656992.jpeg"
  },
  {
    "id": "89e2d3a5-bc3e-4195-b0ec-4fddf41ed6aa",
    "name": "Hábitos de Consumo Alimenticio",
    "category": "Comida y Consumo",
    "description": "Análisis de las preferencias y frecuencia de consumo de distintos tipos de alimentos en la población.",
    "image": "https://images.pexels.com/photos/9070106/pexels-photo-9070106.jpeg"
  },
  {
    "id": "d9e6731c-c5d3-45e0-bb9a-99a7a1f7823b",
    "name": "Opinión sobre Eventos Deportivos Locales",
    "category": "Deportes",
    "description": "Encuesta para conocer la opinión sobre eventos deportivos locales y su organización.",
    "image": "https://images.pexels.com/photos/1464196/pexels-photo-1464196.jpeg"
  },
  {
    "id": "7c348c1f-1aee-42b8-8576-72f1c5b0c2a9",
    "name": "Conciencia sobre Salud Mental",
    "category": "Salud Pública",
    "description": "Encuesta para evaluar el nivel de conciencia sobre la salud mental en diferentes grupos etarios.",
    "image": "https://images.pexels.com/photos/8378740/pexels-photo-8378740.jpeg"
  },
  {
    "id": "a9f23b87-d48c-4f6a-8431-5e14e0e7f674",
    "name": "Tecnología en la Educación",
    "category": "Educación",
    "description": "Opiniones sobre la incorporación de tecnologías en el proceso educativo.",
    "image": "https://images.pexels.com/photos/4145153/pexels-photo-4145153.jpeg"
  },
  {
    "id": "e3c11f9e-879d-4b5c-9f6f-8623c7d1f8e4",
    "name": "Uso de Espacios Verdes Urbanos",
    "category": "Medio Ambiente",
    "description": "Encuesta sobre el uso y mantenimiento de espacios verdes urbanos.",
    "image": "https://siaver.com/modules/ph_simpleblog/covers/7.jpg"
  },
  {
    "id": "11b2a7b1-02de-4c25-b3fa-5bcb30a7f6a8",
    "name": "Preferencias en Comida a Domicilio",
    "category": "Comida y Consumo",
    "description": "Análisis de preferencias y frecuencia en el uso de servicios de comida a domicilio.",
    "image": "https://images.pexels.com/photos/2248097/pexels-photo-2248097.jpeg"
  },
  {
    "id": "3ea2d911-01e7-4ef6-b3a7-c5d47f4e2e07",
    "name": "Hábitos de Fitness Juvenil",
    "category": "Deportes",
    "description": "Estudio sobre los hábitos de ejercicio y actividad física en jóvenes adultos.",
    "image": "https://images.pexels.com/photos/13254061/pexels-photo-13254061.jpeg"
  },
  {
    "id": "4d89e71f-fd4c-4e1d-8edb-2f1182c472a8",
    "name": "Acceso a Servicios de Salud",
    "category": "Salud Pública",
    "description": "Encuesta para evaluar el acceso y calidad de los servicios de salud en zonas rurales.",
    "image": "https://images.pexels.com/photos/6520115/pexels-photo-6520115.jpeg"
  },
  {
    "id": "fb637c1d-85b9-4a5e-92bf-bfc2c40e2b45",
    "name": "Efectividad del E-learning",
    "category": "Educación",
    "description": "Evaluación de la efectividad de plataformas y métodos de aprendizaje en línea.",
    "image": "https://images.pexels.com/photos/4624910/pexels-photo-4624910.jpeg"
  },
  {
    "id": "597ac2f6-9e21-4a61-9c96-56b9e207d362",
    "name": "Comportamiento en Reciclaje",
    "category": "Medio Ambiente",
    "description": "Análisis de comportamientos y hábitos relacionados con el reciclaje domiciliario.",
    "image": "https://images.pexels.com/photos/27674512/pexels-photo-27674512.jpeg"
  },
  {
    "id": "5ea16d47-07fa-4346-8c8d-1391f41f3f29",
    "name": "Consumo de Alimentos Orgánicos",
    "category": "Comida y Consumo",
    "description": "Encuesta sobre el consumo y preferencias de alimentos orgánicos en la población urbana.",
    "image": "https://images.pexels.com/photos/7771964/pexels-photo-7771964.jpeg"
  },
  {
    "id": "4d2a7f9b-cb11-4e56-b930-2f5d462b7d91",
    "name": "Programas Deportivos Comunitarios",
    "category": "Deportes",
    "description": "Evaluación de la participación y satisfacción con programas deportivos comunitarios.",
    "image": "https://images.pexels.com/photos/6646917/pexels-photo-6646917.jpeg"
  },
  {
    "id": "828e679a-3ccf-4e6e-a9a9-79ed7f1e7ecf",
    "name": "Conciencia sobre Vacunación",
    "category": "Salud Pública",
    "description": "Encuesta sobre el conocimiento y aceptación de programas de vacunación.",
    "image": "https://images.pexels.com/photos/5206956/pexels-photo-5206956.jpeg"
  },
  {
    "id": "2a3d8f4c-8c1e-4d27-857a-f3bc5eaf937d",
    "name": "Satisfacción de Docentes",
    "category": "Educación",
    "description": "Medición del nivel de satisfacción y condiciones laborales de los docentes.",
    "image": "https://images.pexels.com/photos/7172858/pexels-photo-7172858.jpeg"
  },
  {
    "id": "c1f77622-2d95-4d59-85e7-53fcd923a6f4",
    "name": "Percepción sobre Calidad del Aire",
    "category": "Medio Ambiente",
    "description": "Opiniones sobre la calidad del aire y sus efectos en la salud pública.",
    "image": "https://images.pexels.com/photos/7959345/pexels-photo-7959345.jpeg"
  },
  {
    "id": "d71a9a8f-3f7b-4e8c-b10c-92aaf985a4e6",
    "name": "Tendencias en Consumo de Comida Rápida",
    "category": "Comida y Consumo",
    "description": "Análisis de tendencias en el consumo de comida rápida entre diferentes grupos de edad.",
    "image": "https://images.pexels.com/photos/8467224/pexels-photo-8467224.jpeg"
  }
]
